ai_snake_lab/ai/AIAgent.py
ai_snake_lab/ai/AITrainer.py
ai_snake_lab/ai/EpsilonAlgo.py
ai_snake_lab/ai/EpsilonAlgoN.py
ai_snake_lab/ai/ReplayMemory.py
ai_snake_lab/ai/models/ModelL.py
ai_snake_lab/ai/models/ModelRNN.py
ai_snake_lab/ai/models/ModelT.py
ai_snake_lab/constants/DAIAgent.py
ai_snake_lab/constants/DColors.py
ai_snake_lab/constants/DDef.py
ai_snake_lab/constants/DDir.py
ai_snake_lab/constants/DEpsilon.py
ai_snake_lab/constants/DFile.py
ai_snake_lab/constants/DLabLogger.py
ai_snake_lab/constants/DLabels.py
ai_snake_lab/constants/DLayout.py
ai_snake_lab/constants/DMQ.py
ai_snake_lab/constants/DModelL.py
ai_snake_lab/constants/DModelLRNN.py
ai_snake_lab/constants/DPlot.py
ai_snake_lab/constants/DReplayMemory.py
ai_snake_lab/constants/DSim.py
ai_snake_lab/constants/__init__.py
ai_snake_lab/game/ClientGameBoard.py
ai_snake_lab/game/GameBoard.py
ai_snake_lab/game/GameElements.py
ai_snake_lab/game/ServerGameBoard.py
ai_snake_lab/game/SnakeGame.py
ai_snake_lab/server/SimRouter.py
ai_snake_lab/server/SimServer.py
ai_snake_lab/ui/AISim.tcss
ai_snake_lab/ui/SimClient.py
ai_snake_lab/ui/TabbedPlots.py
ai_snake_lab/utils/ConstGroup.py
ai_snake_lab/utils/DBMgr.py
ai_snake_lab/utils/LabLogger.py
ai_snake_lab/utils/MQHelper.py
ai_snake_lab-0.12.0.dist-info/METADATA
ai_snake_lab-0.12.0.dist-info/WHEEL
ai_snake_lab-0.12.0.dist-info/entry_points.txt
ai_snake_lab-0.12.0.dist-info/licenses/LICENSE
ai_snake_lab-0.12.0.dist-info/RECORD
